uugai_python_color_prediction/ColorPrediction.py
uugai_python_color_prediction/__init__.py
uugai_python_color_prediction-3.0.0.dist-info/METADATA
uugai_python_color_prediction-3.0.0.dist-info/WHEEL
uugai_python_color_prediction-3.0.0.dist-info/top_level.txt
uugai_python_color_prediction-3.0.0.dist-info/RECORD
