Metadata-Version: 2.1
Name: uugai-python-color-prediction
Version: 3.0.0
Summary: Color prediction Python library used to find the main colors in an image.
Home-page: UNKNOWN
Author: uug.ai
Author-email: support@uug.ai
License: UNKNOWN
Platform: UNKNOWN
Requires-Dist: contourpy (==1.2.1)
Requires-Dist: cycler (==0.12.1)
Requires-Dist: fonttools (==4.51.0)
Requires-Dist: joblib (==1.4.2)
Requires-Dist: kiwisolver (==1.4.5)
Requires-Dist: kneed (==0.8.5)
Requires-Dist: matplotlib (==3.9.0)
Requires-Dist: numpy (==1.26.4)
Requires-Dist: opencv-python (==4.9.0.80)
Requires-Dist: packaging (==24.0)
Requires-Dist: pillow (==10.3.0)
Requires-Dist: pyparsing (==3.1.2)
Requires-Dist: python-dateutil (==2.9.0.post0)
Requires-Dist: scikit-learn (==1.5.0)
Requires-Dist: scipy (==1.13.1)
Requires-Dist: setuptools (==70.0.0)
Requires-Dist: six (==1.16.0)
Requires-Dist: threadpoolctl (==3.5.0)
